MeteorClient
