Metadata-Version: 1.1
Name: python-meteor
Version: 0.1.5
Summary: An event driven meteor client
Home-page: https://github.com/hharnisc/python-meteor
Author: Harrison Harnisch
Author-email: hharnisc@gmail.com
License: MIT
Keywords: meteor,ddp,events,emitter,node.js,node,eventemitter,event_emitter,ejson
Platform: UNKNOWN
Classifier: Programming Language :: Python
Classifier: Development Status :: 2 - Pre-Alpha
Classifier: Intended Audience :: Developers
Classifier: License :: OSI Approved :: MIT License
Classifier: Operating System :: OS Independent
Classifier: Programming Language :: Python :: 2.7
Classifier: Topic :: Other/Nonlisted Topic
